rss_reader/__init__.py
rss_reader/__main__.py
rss_reader/argument_parser/__init__.py
rss_reader/argument_parser/_argparser.py
rss_reader/config/__init__.py
rss_reader/config/_config.py
rss_reader/converter/__init__.py
rss_reader/converter/_converter.py
rss_reader/printer/__init__.py
rss_reader/printer/_printer.py
rss_reader/reader/__init__.py
rss_reader/reader/_caching.py
rss_reader/reader/_reader.py
rss_reader/rss_builder/__init__.py
rss_reader/rss_builder/_builder.py
rss_reader/rss_builder/_rss_models.py
rss_reader/rss_builder/_url_resolver.py
rss_reader/xml_parser/__init__.py
rss_reader/xml_parser/_parser.py
rss_reader/xml_parser/_parser_models.py
rss_reader/xml_parser/_tokenizer.py
tests/__init__.py
tests/test_builder.py
tests/test_caching.py
tests/test_parser.py
markedrss-3.2.2.dist-info/LICENSE.txt
markedrss-3.2.2.dist-info/METADATA
markedrss-3.2.2.dist-info/WHEEL
markedrss-3.2.2.dist-info/entry_points.txt
markedrss-3.2.2.dist-info/top_level.txt
markedrss-3.2.2.dist-info/RECORD
