Metadata-Version: 2.1
Name: markedrss
Version: 3.2.2
Summary: Pure Python command-line RSS reader
Home-page: https://github.com/doppelmarker/Homework
Author: doppelmarker
Author-email: doppelmarker@gmail.com
License: MIT
Platform: UNKNOWN
Requires-Python: >=3.9
License-File: LICENSE.txt
Requires-Dist: requests
Requires-Dist: pydantic
Requires-Dist: Jinja2
Requires-Dist: xhtml2pdf
Requires-Dist: ebooklib
Requires-Dist: colorama
Provides-Extra: aiohttp
Requires-Dist: aiohttp ; extra == 'aiohttp'
